tesorotools/__init__.py
tesorotools/convert.py
tesorotools/main.py
tesorotools/artists/__init__.py
tesorotools/artists/barh_plot.py
tesorotools/artists/line_plot.py
tesorotools/artists/table.py
tesorotools/artists/type_curve.py
tesorotools/assets/README.md
tesorotools/assets/plots.yaml
tesorotools/assets/tesoro.mplstyle
tesorotools/assets/fonts/CabinetGrotesk-Black.otf
tesorotools/assets/fonts/CabinetGrotesk-Bold.otf
tesorotools/assets/fonts/CabinetGrotesk-Extrabold.otf
tesorotools/assets/fonts/CabinetGrotesk-Extralight.otf
tesorotools/assets/fonts/CabinetGrotesk-Light.otf
tesorotools/assets/fonts/CabinetGrotesk-Medium.otf
tesorotools/assets/fonts/CabinetGrotesk-Regular.otf
tesorotools/assets/fonts/CabinetGrotesk-Thin.otf
tesorotools/assets/fonts/README.md
tesorotools/data_sources/README.md
tesorotools/data_sources/__init__.py
tesorotools/data_sources/debug.py
tesorotools/data_sources/lseg.py
tesorotools/database/__init__.py
tesorotools/database/local.py
tesorotools/database/push.py
tesorotools/dependencies/__init__.py
tesorotools/dependencies/functions.py
tesorotools/dependencies/node.py
tesorotools/dependencies/resolution.py
tesorotools/offsets/__init__.py
tesorotools/offsets/offsets.py
tesorotools/offsets/outliers.py
tesorotools/render/__init__.py
tesorotools/render/report.py
tesorotools/render/content/__init__.py
tesorotools/render/content/content.py
tesorotools/render/content/images.py
tesorotools/render/content/section.py
tesorotools/render/content/subtitle.py
tesorotools/render/content/table.py
tesorotools/render/content/text.py
tesorotools/render/content/title.py
tesorotools/utils/__init__.py
tesorotools/utils/config.py
tesorotools/utils/format.py
tesorotools/utils/globals.py
tesorotools/utils/matplotlib.py
tesorotools/utils/series.py
tesorotools/utils/shortcuts.py
tesorotools/utils/template.py
tesorotools_python-0.0.21.dist-info/METADATA
tesorotools_python-0.0.21.dist-info/WHEEL
tesorotools_python-0.0.21.dist-info/RECORD
