Metadata-Version: 2.4
Name: tesorotools-python
Version: 0.0.21
Requires-Python: >=3.13
Requires-Dist: babel
Requires-Dist: eikon
Requires-Dist: lseg-data
Requires-Dist: matplotlib
Requires-Dist: openpyxl
Requires-Dist: pandas
Requires-Dist: psycopg2
Requires-Dist: pyarrow
Requires-Dist: python-docx
Requires-Dist: pywin32>=311; sys_platform != 'linux'
Requires-Dist: pyyaml
Requires-Dist: sqlalchemy
